agxBrick/__init__.py
agxBrick/__main__.py
agxBrick/brickLoaderUtils.py
agxBrick/brickRos2ControllerUtils.py
agxBrick/brickRosListener.py
agxBrick/brickViewPositioning.py
agxBrick/brick_env.py
agxBrick/brick_gym_env.py
agxBrick/brickapp_initiates_ExampleApplication.py
agxBrick/keyPoller.py
agxBrick/loadBrickModel.py
agxBrick/loadBrickModelController.py
agxBrick/loadBrickPlot.py
agxBrick/loadTest.py
agxBrick/run_brick.py
agxBrick/dist/.brick_ignore
agxBrick/dist/AGXBrick/Brick.AGXBrick.deps.json
agxBrick/dist/AGXBrick/Brick.AGXBrick.dll
agxBrick/dist/AGXBrick/Brick.AGXBrick.pdb
agxBrick/dist/AGXBrick/Brick.AGXBrick.runtimeconfig.json
agxBrick/dist/AGXBrick/Brick.AGXBrickViewer
agxBrick/dist/AGXBrick/Brick.AGXBrickViewer.deps.json
agxBrick/dist/AGXBrick/Brick.AGXBrickViewer.dll
agxBrick/dist/AGXBrick/Brick.AGXBrickViewer.pdb
agxBrick/dist/AGXBrick/Brick.AGXBrickViewer.runtimeconfig.json
agxBrick/dist/AGXBrick/Brick.Core.dll
agxBrick/dist/AGXBrick/Brick.Geometry.dll
agxBrick/dist/AGXBrick/Brick.MachineLearning.dll
agxBrick/dist/AGXBrick/Brick.Math.dll
agxBrick/dist/AGXBrick/Brick.Physics.dll
agxBrick/dist/AGXBrick/Brick.ROS.dll
agxBrick/dist/AGXBrick/Brick.Robotics.dll
agxBrick/dist/AGXBrick/Brick.Scene.dll
agxBrick/dist/AGXBrick/Brick.Signal.dll
agxBrick/dist/AGXBrick/Brick.Simulation.dll
agxBrick/dist/AGXBrick/Brick.Visual.dll
agxBrick/dist/AGXBrick/CommandLine.dll
agxBrick/dist/AGXBrick/Common.Logging.Core.dll
agxBrick/dist/AGXBrick/Common.Logging.dll
agxBrick/dist/AGXBrick/DotNet.Glob.dll
agxBrick/dist/AGXBrick/FastExpressionCompiler.dll
agxBrick/dist/AGXBrick/MIConvexHull.dll
agxBrick/dist/AGXBrick/Makaretu.Dns.Multicast.dll
agxBrick/dist/AGXBrick/Makaretu.Dns.dll
agxBrick/dist/AGXBrick/Microsoft.Extensions.Configuration.Abstractions.dll
agxBrick/dist/AGXBrick/Microsoft.Extensions.DependencyInjection.Abstractions.dll
agxBrick/dist/AGXBrick/Microsoft.Extensions.FileProviders.Abstractions.dll
agxBrick/dist/AGXBrick/Microsoft.Extensions.FileSystemGlobbing.dll
agxBrick-0.6.0.dist-info/METADATA
agxBrick-0.6.0.dist-info/WHEEL
agxBrick-0.6.0.dist-info/top_level.txt
agxBrick-0.6.0.dist-info/RECORD
