Metadata-Version: 2.1
Name: agxBrick
Version: 0.6.0
Summary: Core framework, API and runtime, for generic data modelling, and construction of domain specific modelling APIs/formats. Specifically supporting modelling of simulation components.
Author: Algoryx
Author-email: algoryx@algoryx.com
Classifier: Development Status :: 3 - Alpha
Classifier: Programming Language :: Python :: 3.6
Requires-Python: >=3.7
Requires-Dist: click (>=7.1.2)
Requires-Dist: coloredlogs (>=15.0)
Provides-Extra: dev
Requires-Dist: check-manifest ; extra == 'dev'
Provides-Extra: test
